{
  "message": "🔧 Refactoring is like cleaning your room - it feels great afterward!",
  "svg": "<div align=\"center\">\n  <img src=\"chat_conversation.svg\" alt=\"AI Chat Bubble\" />\n</div>",
  "timestamp": "2026-01-17T08:04:54.221182",
  "last_updated": "January 17, 2026 at 08:04 UTC",
  "all_messages": [
    "🔧 Refactoring is like cleaning your room - it feels great afterward!",
    "🤖 Did you know? The first computer bug was an actual bug - a moth stuck in a relay!",
    "💫 Passionate engineer fueled by curiosity and great coffee! Reach me at https://ph7.me"
  ]
}