{
  "message": "🎯 Focus on progress, not perfection. You've got this!",
  "svg": "<div align=\"center\">\n  <img src=\"chat_conversation.svg\" alt=\"AI Chat Bubble\" />\n</div>",
  "timestamp": "2026-05-07T08:54:25.241018",
  "last_updated": "May 07, 2026 at 08:54 UTC",
  "all_messages": [
    "🎯 Focus on progress, not perfection. You've got this!",
    "💫 Passionate engineer fueled by curiosity and great coffee! Reach me at https://ph7.me",
    "📊 Fun fact: JavaScript was created in just 10 days!"
  ]
}