{
  "message": "🚀 Dream in code, build in reality, ship with confidence!",
  "svg": "<div align=\"center\">\n  <img src=\"chat_conversation.svg\" alt=\"AI Chat Bubble\" />\n</div>",
  "timestamp": "2026-06-02T20:57:40.706418",
  "last_updated": "June 02, 2026 at 20:57 UTC",
  "all_messages": [
    "🚀 Dream in code, build in reality, ship with confidence!",
    "🌱 Green coding practices help save our planet!",
    "🍇 Daily fuel check: Learning ✅ Coding ✅ Researching ✅ Fruit ✅ Hiking ✅ Energized! 😊"
  ]
}